{"articles_lib_dayjs.md":"30f08805","articles_css_postcss配置.md":"bde71620","articles_css_tailwindcss.md":"a0faea53","articles_lib_canvas.md":"b828920d","notes_图床.md":"7808194c","articles_lib_index.md":"535b7007","project_onlineoffice.md":"591ab39b","project_lowcode.md":"373f9b6a","articles_typescript.md":"239cb8d6","project_ide.md":"fa166751","tool_index.md":"e9d133e6","index.md":"3a9c677e","project_flutter.md":"0605828c","project_video.md":"eb5b37a2","notes_index.md":"980ad295","articles_cli.md":"4e5c0c4e","articles_blender_3d模型-光源-动画.md":"655d5379","articles_blender_blender建模地形.md":"f954cf7d","tool_gitpage.md":"a1f45ae9","articles_index.md":"9d349d87","articles_css_scss.md":"c0e8b143","nav_index.md":"5157c92d","tool_通义灵码使用.md":"6991b092","articles_lib_3d.md":"351bbd83","project_electron.md":"c02e7c4d","project_index.md":"119363d0","articles_threejs_threejs.md":"ffc9e823","articles_threejs_threejs-env.md":"dc3272df","articles_blender_blender快捷键.md":"07c78b34","articles_css_css原子样式.md":"fe9ea052","articles_lib_office.md":"0c99fafa","tool_vscode.md":"0a43ed5e","notes_常用正则.md":"d889fd26","articles_packagejson指南.md":"cf74d2f9","notes_yarn.md":"a0510f50","notes_css生成器.md":"e2cdc230","tool_mdsyntax.md":"f2a5d193","articles_commonjs与esmodule.md":"899f5d2c","project_canvas.md":"96c1d87c","project_threejs.md":"e3d4e36c","project_editor.md":"f03354de","articles_https_axios.md":"a06810d7","articles_css_常用css.md":"efb6c528","notes_常用代码片段.md":"4085b9eb","tool_git.md":"533078bc","articles_css_css通用默认样式.md":"1b6323fd"}
